AUTHORS.rst
CHANGELOG.rst
LICENSE
MANIFEST.in
README.rst
setup.py
django_googlesearch.egg-info/PKG-INFO
django_googlesearch.egg-info/SOURCES.txt
django_googlesearch.egg-info/dependency_links.txt
django_googlesearch.egg-info/not-zip-safe
django_googlesearch.egg-info/requires.txt
django_googlesearch.egg-info/top_level.txt
googlesearch/__init__.py
googlesearch/models.py
googlesearch/tests.py
googlesearch/urls.py
googlesearch/views.py
googlesearch/templates/googlesearch/cref_cse.xml
googlesearch/templates/googlesearch/results.html
googlesearch/templates/googlesearch/inclusion_tags/form.html
googlesearch/templates/googlesearch/inclusion_tags/results.html
googlesearch/templatetags/__init__.py
googlesearch/templatetags/__init__.pyc
googlesearch/templatetags/googlesearch_inclusion_tags.py
googlesearch/templatetags/googlesearch_inclusion_tags.pyc